agh_vqis/__init__.py
agh_vqis/__main__.py
agh_vqis/_logger.py
agh_vqis/binaries/agh_vqis_linux_aarch64_mt
agh_vqis/binaries/agh_vqis_linux_x86_64_mt
agh_vqis/binaries/agh_vqis_macosx_arm64_mt
agh_vqis/binaries/agh_vqis_macosx_x86_64_mt
agh_vqis/binaries/agh_vqis_win64_mt.exe
agh_vqis/binaries/cygwin1.dll
agh_vqis/models/resolution_cast/model_Blockiness_1080p_1440p.xgb
agh_vqis/models/resolution_cast/model_Blockiness_1080p_2160p.xgb
agh_vqis/models/resolution_cast/model_Blockiness_1440p_2160p.xgb
agh_vqis/models/resolution_cast/model_Blockiness_2160p_1440p.xgb
agh_vqis/models/resolution_cast/model_Blur_1080p_1440p.xgb
agh_vqis/models/resolution_cast/model_Blur_1080p_2160p.xgb
agh_vqis/models/resolution_cast/model_Blur_1440p_1080p.xgb
agh_vqis/models/resolution_cast/model_Blur_1440p_2160p.xgb
agh_vqis/models/resolution_cast/model_Blur_2160p_1080p.xgb
agh_vqis/models/resolution_cast/model_Blur_2160p_1440p.xgb
agh_vqis/models/resolution_cast/model_Blur_240p_360p.xgb
agh_vqis/models/resolution_cast/model_Blur_240p_480p.xgb
agh_vqis/models/resolution_cast/model_Blur_360p_240p.xgb
agh_vqis/models/resolution_cast/model_Blur_360p_480p.xgb
agh_vqis/models/resolution_cast/model_Blur_360p_720p.xgb
agh_vqis/models/resolution_cast/model_Blur_480p_240p.xgb
agh_vqis/models/resolution_cast/model_Blur_480p_360p.xgb
agh_vqis/models/resolution_cast/model_Blur_480p_720p.xgb
agh_vqis/models/resolution_cast/model_Blur_720p_1080p.xgb
agh_vqis/models/resolution_cast/model_Blur_720p_360p.xgb
agh_vqis/models/resolution_cast/model_Blur_720p_480p.xgb
agh_vqis/models/resolution_cast/model_Contrast_1080p_1440p.xgb
agh_vqis/models/resolution_cast/model_Contrast_1080p_2160p.xgb
agh_vqis/models/resolution_cast/model_Contrast_1080p_240p.xgb
agh_vqis/models/resolution_cast/model_Contrast_1080p_360p.xgb
agh_vqis/models/resolution_cast/model_Contrast_1080p_480p.xgb
agh_vqis/models/resolution_cast/model_Contrast_1080p_720p.xgb
agh_vqis/models/resolution_cast/model_Contrast_1440p_1080p.xgb
agh_vqis-3.4.6.dist-info/licenses/LICENSE
agh_vqis-3.4.6.dist-info/METADATA
agh_vqis-3.4.6.dist-info/WHEEL
agh_vqis-3.4.6.dist-info/top_level.txt
agh_vqis-3.4.6.dist-info/RECORD
