Metadata-Version: 2.4
Name: agh_vqis
Version: 3.4.6
Summary: A Python wrapper for 18 image quality indicators.
Home-page: https://qoe.agh.edu.pl/indicators/
Author: Filip Korus, Jakub Nawała
Author-email: fkorus@student.agh.edu.pl, jakub.nawala@agh.edu.pl
License: EVALUATION LICENSE AGREEMENT
Classifier: Programming Language :: Python :: 3
Classifier: Programming Language :: Python :: 3.9
Classifier: Programming Language :: Python :: 3.10
Classifier: Programming Language :: Python :: 3.11
Classifier: Programming Language :: Python :: 3.12
Classifier: License :: Other/Proprietary License
Classifier: Operating System :: POSIX :: Linux
Classifier: Operating System :: Microsoft :: Windows
Classifier: Operating System :: MacOS
Classifier: Intended Audience :: Science/Research
Classifier: Intended Audience :: Telecommunications Industry
Classifier: Topic :: Multimedia :: Video
Classifier: Topic :: Scientific/Engineering :: Image Processing
Requires-Python: >=3.9
License-File: LICENSE
Requires-Dist: matplotlib>=3.5.1
Requires-Dist: numpy<2.1.0,>=1.26.0
Requires-Dist: pandas==2.2.2
Requires-Dist: PIMS>=0.7
Requires-Dist: scikit-image>=0.25.2
Requires-Dist: slicerator>=1.1.0
Requires-Dist: scenedetect>=0.6.6
Requires-Dist: opencv-python>=4.11.0.86
Requires-Dist: xgboost==1.7.5
Requires-Dist: scikit-learn==1.6.1
Requires-Dist: av>=14.3.0
Requires-Dist: ffmpeg-python>=0.2.0
Dynamic: license-file
